fuzzytable/__init__.py
fuzzytable/cellpatterns.py
fuzzytable/exceptions.py
fuzzytable/_docstringfiles/cities.csv
fuzzytable/_docstringfiles/colors.csv
fuzzytable/_docstringfiles/warm_colors.csv
fuzzytable/datamodel/__init__.py
fuzzytable/datamodel/fields.py
fuzzytable/datamodel/records.py
fuzzytable/datamodel/sheet.py
fuzzytable/main/fuzzytable.py
fuzzytable/main/sheetreader.py
fuzzytable/main/string_analysis.py
fuzzytable/main/utils.py
fuzzytable/parsers/__init__.py
fuzzytable/parsers/fieldparser.py
fuzzytable/parsers/sheetparser.py
fuzzytable/patterns/__init__.py
fuzzytable/patterns/cellpattern.py
fuzzytable/patterns/fieldpattern.py
fuzzytable/patterns/sheetpattern.py
fuzzytable-0.19.dist-info/LICENSE
fuzzytable-0.19.dist-info/WHEEL
fuzzytable-0.19.dist-info/METADATA
fuzzytable-0.19.dist-info/RECORD
