Metadata-Version: 2.1
Name: fuzzytable
Version: 0.19
Summary: Read tables from messy spreadsheets.
Home-page: https://github.com/jonathanchukinas/fuzzytable
License: UNKNOWN
Keywords: xlrd openpyxl Excel xlsx xls excel csv fuzzy table spreadsheet
Author: Jonathan Chukinas
Author-email: chukinas@gmail.com
Requires-Python: >=3.6.3
Classifier: Development Status :: 2 - Pre-Alpha
Classifier: Intended Audience :: Developers
Classifier: Intended Audience :: End Users/Desktop
Classifier: License :: OSI Approved :: MIT License
Classifier: Natural Language :: English
Classifier: Operating System :: Microsoft :: Windows :: Windows 10
Classifier: Operating System :: OS Independent
Classifier: Programming Language :: Python :: 3
Classifier: Programming Language :: Python :: 3.6
Classifier: Programming Language :: Python :: 3.7
Classifier: Programming Language :: Python :: 3.8
Requires-Dist: openpyxl==3.0.0
Requires-Dist: sphinx; extra == "doc"
Requires-Dist: m2r; extra == "doc"
Requires-Dist: autodocsumm; extra == "doc"
Requires-Dist: pytest; extra == "test"
Requires-Dist: pytest-cov; extra == "test"
Requires-Dist: tox; extra == "test"
Requires-Dist: names; extra == "test"
Project-URL: Documentation, https://fuzzytable.readthedocs.io/
Project-URL: Tracker, https://github.com/jonathanchukinas/fuzzytable/issues
Provides-Extra: doc
Provides-Extra: test
